setup.py
prime_tools/__init__.py
prime_tools/prime_factorization.py
prime_tools/prime_generation.py
prime_tools.egg-info/PKG-INFO
prime_tools.egg-info/SOURCES.txt
prime_tools.egg-info/dependency_links.txt
prime_tools.egg-info/not-zip-safe
prime_tools.egg-info/top_level.txt