Metadata-Version: 1.0
Name: prime-tools
Version: 0.2.2
Summary: Tools for prime factorization and prime number generation
Home-page: https://pypi.python.org/pypi/prime_tools
Author: Christopher Nugent
Author-email: awedeven@gmail.com
License: none
Platform: UNKNOWN
